aioblescan/__init__.py
aioblescan/__main__.py
aioblescan/aioblescan.py
aioblescan/plugins/__init__.py
aioblescan/plugins/atcmithermometer.py
aioblescan/plugins/eddystone.py
aioblescan/plugins/ruuviweather.py
aioblescan/plugins/thermobeacon.py
aioblescan/plugins/tilt.py
aioblescan-0.2.14.dist-info/LICENSE.txt
aioblescan-0.2.14.dist-info/METADATA
aioblescan-0.2.14.dist-info/WHEEL
aioblescan-0.2.14.dist-info/entry_points.txt
aioblescan-0.2.14.dist-info/top_level.txt
aioblescan-0.2.14.dist-info/RECORD
