Metadata-Version: 2.1
Name: aioblescan
Version: 0.2.14
Summary: Scanning Bluetooth for advertised info with asyncio.
Home-page: http://github.com/frawau/aioblescan
Author: François Wautier
Author-email: francois@wautier.eu
License: MIT
Keywords: bluetooth,advertising,hci,ble
Platform: UNKNOWN
Classifier: License :: OSI Approved :: MIT License
Classifier: Programming Language :: Python :: 3.7
Classifier: Programming Language :: Python :: 3.8
Classifier: Programming Language :: Python :: 3.9
Classifier: Programming Language :: Python :: 3.10
Provides-Extra: dev
License-File: LICENSE.txt
